de1/__init__.py
de1/empty/__init__.py
de1/empty/empty_partitioned_data_set.py
de1/lazy/__init__.py
de1/lazy/lazy_partitioend_data_set.py
de1/pdf/__init__.py
de1/pdf/pdf_data_set.py
de1/pdf/pdf_page.py
de1/tests/__init__.py
de1/tests/test_empty/__init__.py
de1/tests/test_empty/test_empty_partitioned_data_set.py
de1/tests/test_lazy/__init__.py
de1/tests/test_lazy/test_lazy_partitioned_data_set.py
de1/tests/test_pdf/__init__.py
de1/tests/test_pdf/test_pdf_data_set.py
de1/tests/test_zip/__init__.py
de1/tests/test_zip/test_zip_file_data_set.py
de1/zip/__init__.py
de1/zip/zip_file_data_set.py
de1-0.1.1.dist-info/METADATA
de1-0.1.1.dist-info/WHEEL
de1-0.1.1.dist-info/top_level.txt
de1-0.1.1.dist-info/zip-safe
de1-0.1.1.dist-info/RECORD
